cfnlambda.py
cfnlambda-1.0.1.dist-info/DESCRIPTION.rst
cfnlambda-1.0.1.dist-info/METADATA
cfnlambda-1.0.1.dist-info/RECORD
cfnlambda-1.0.1.dist-info/WHEEL
cfnlambda-1.0.1.dist-info/metadata.json
cfnlambda-1.0.1.dist-info/top_level.txt
