Metadata-Version: 2.0
Name: cfnlambda
Version: 1.0.1
Summary: Collection of tools to enable use of AWS Lambda with CloudFormation.
Home-page: https://github.com/gene1wood/cfnlambda
Author: Gene Wood
Author-email: gene_wood@cementhorizon.com
License: MPL-2.0
Keywords: aws lambda cloudformation
Platform: UNKNOWN
Classifier: Development Status :: 4 - Beta
Classifier: Intended Audience :: Developers
Classifier: License :: OSI Approved :: Mozilla Public License 2.0 (MPL 2.0)
Classifier: Programming Language :: Python :: 2.7
Requires-Dist: boto3
Requires-Dist: botocore
